multiscale_run/__init__.py
multiscale_run/bloodflow_manager.py
multiscale_run/cli.py
multiscale_run/config.py
multiscale_run/connection_manager.py
multiscale_run/metabolism_manager.py
multiscale_run/neurodamus_manager.py
multiscale_run/preprocessor.py
multiscale_run/reporter.py
multiscale_run/simulation.py
multiscale_run/steps_manager.py
multiscale_run/utils.py
multiscale_run/data/__init__.py
multiscale_run/data/postproc.ipynb
multiscale_run/data/simulation.sbatch.jinja
multiscale_run/data/config/msr.schema.json
multiscale_run/data/config/rat_sscxS1HL_V10/circuit_config.json
multiscale_run/data/config/rat_sscxS1HL_V10/node_sets.json
multiscale_run/data/config/rat_sscxS1HL_V10/simulation_config.json
multiscale_run/data/config/rat_sscxS1HL_V6/circuit_config.json
multiscale_run/data/config/rat_sscxS1HL_V6/node_sets.json
multiscale_run/data/config/rat_sscxS1HL_V6/simulation_config.json
multiscale_run/data/metabolismndam_reduced/julia_gen_18feb2021.jl
multiscale_run/data/metabolismndam_reduced/met4cns.jl
multiscale_run/data/metabolismndam_reduced/metabolismWithSBBFinput_ndamAdapted_opt_sys_young_202302210826_2stim.jl
multiscale_run/data/metabolismndam_reduced/metabolism_model_21nov22_noEphys_noSB.jl
multiscale_run/data/metabolismndam_reduced/metabolism_model_21nov22_withEphysCurrNdam_noSB.jl
multiscale_run/data/metabolismndam_reduced/metabolism_model_21nov22_withEphysNoCurrNdam_noSB.jl
multiscale_run/data/metabolismndam_reduced/u0_Calv_ATP_1p4_Nai10.csv
multiscale_run/data/metabolismndam_reduced/u0steady_22nov22.csv
multiscale_run-0.8.2.dist-info/AUTHORS.txt
multiscale_run-0.8.2.dist-info/LICENSE.txt
multiscale_run-0.8.2.dist-info/METADATA
multiscale_run-0.8.2.dist-info/WHEEL
multiscale_run-0.8.2.dist-info/entry_points.txt
multiscale_run-0.8.2.dist-info/top_level.txt
multiscale_run-0.8.2.dist-info/RECORD
