Metadata-Version: 2.1
Name: multiscale_run
Version: 0.8.2
Summary: MultiscaleRun is a Python package to run brain cells simulation at different scales. It orchestrates the coupling between several brain simulators like Neuron and STEPS but also solvers like AstroVascPy for the cerebral blood flow. The package also embeds a Julia solver to simulate the astrocytes activity. 
Author-email: "Blue Brain Project, EPFL" <bbp.opensource@epfl.ch>
License: Apache-2.0
Project-URL: Homepage, https://multiscalerun.rtfd.io
Project-URL: Source, https://github.com/BlueBrain/MultiscaleRun.git
Project-URL: Tracker, https://github.com/BlueBrain/MultiscaleRun/issues
Classifier: Development Status :: 4 - Beta
Classifier: Intended Audience :: Education
Classifier: Intended Audience :: Science/Research
Classifier: Programming Language :: Python :: 3
Classifier: Topic :: Scientific/Engineering :: Bio-Informatics
Requires-Python: >=3.8
License-File: LICENSE.txt
License-File: AUTHORS.txt
Requires-Dist: astrovascpy>=0.1.5
Requires-Dist: bluepysnap>=2
Requires-Dist: diffeqpy>=1.1
Requires-Dist: gmsh>=4.2
Requires-Dist: jinja2>=3
Requires-Dist: jsonschema>=4
Requires-Dist: julia<0.7,>=0.6
Requires-Dist: libsonata>=0.1.20
Requires-Dist: mpi4py>=3
Requires-Dist: notebook>=6
Requires-Dist: numpy>=1.22
Requires-Dist: pandas>=1.4
Requires-Dist: psutil>=5.8
Requires-Dist: scipy>=1.11.1
Requires-Dist: simpleeval>=0.9.13
Requires-Dist: tqdm>=4.65
Requires-Dist: trimesh>=3
Provides-Extra: docs
Requires-Dist: mistune<3; extra == "docs"
Requires-Dist: sphinx; extra == "docs"
Requires-Dist: sphinx-bluebrain-theme; extra == "docs"
Requires-Dist: sphinx-mdinclude; extra == "docs"
